medr00t/__init__.py
medr00t/sql.py
medr00t_driver-0.0.dist-info/METADATA
medr00t_driver-0.0.dist-info/WHEEL
medr00t_driver-0.0.dist-info/top_level.txt
medr00t_driver-0.0.dist-info/RECORD
