Metadata-Version: 2.1
Name: medr00t-driver
Version: 0.0
Summary: A package to create PyQt5 Driver connector for MySQL integration automatically
Author: Med Amine El Ansari
Author-email: Med Amine El Ansari <aminemed.elansari@uic.ac.ma>
Classifier: Programming Language :: Python :: 3
Classifier: Operating System :: OS Independent
Requires-Dist: mysql-connector-python>=8.0
Requires-Dist: PyQt5>=5.15
